Metadata-Version: 2.1
Name: fake-rpi-plus
Version: 0.2
Summary: Fake RPi
Home-page: https://github.com/aldonald/fake_rpi
Author: Original: MomsFriendlyRobotCompany fake_rpi
Author-email: 
License: UNKNOWN
Platform: UNKNOWN
Classifier: Programming Language :: Python :: 3
Classifier: License :: OSI Approved :: MIT License
Classifier: Operating System :: OS Independent
